Workbook

Sheet Assumptions
A1: TokenOasis — Pricing & Margin Model
A2: Blue = inputs you change. Black = formulas. Green = links.
A4: PRICING & MARGIN
A5: Markup multiplier (retail ÷ cost) | B5: 1.3 | C5: Profit lever. 1.30 = +30%. MARKUP_BPS=13000 in code.
A6: Stripe % fee | B6: 0.029 | C6: Card processing
A7: Stripe per-transaction fee | B7: 0.3 | C7: Per purchase
A9: REPRESENTATIVE CALL
A10: Avg input tokens / call | B10: 800
A11: Avg output tokens / call | B11: 400
A12: Model (for blended unit economics) | B12: gpt-4o-mini | C12: Pick your highest-volume model
A13: Input price ($ / 1M tokens) | B13: 0.15 | C13: Source: OpenAI API pricing 2026 (verify live)
A14: Output price ($ / 1M tokens) | B14: 0.6 | C14: Source: OpenAI API pricing 2026 (verify live)
A16: DEMAND
A17: Active paying users | B17: 500
A18: Avg cash spend / user / month | B18: 40
A19: Blended bonus credit % | B19: 0.07 | C19: Weighted avg across packages
A20: Purchases / user / month | B20: 1
A22: FIXED MONTHLY COSTS
A23: Hosting / infrastructure | B23: 800
A24: Salaries / contractors | B24: 6000
A25: Tools / other | B25: 500
A26: Total fixed monthly cost | B26: =SUM(B23:B25) -> 7300

Sheet Unit Economics
A1: Unit Economics
A3: PER CALL
A4: Provider cost / call | B4: =(Assumptions!B10*Assumptions!B13+Assumptions!B11*Assumptions!B14)/1000000 -> 0.00036
A5: Retail charge / call | B5: =B4*Assumptions!B5 -> 0.000468
A6: Gross profit / call | B6: =B5-B4 -> 0.000108
A7: Gross margin % | B7: =B6/B5 -> 0.23076923
A9: CREDIT PACKAGES
A10: Package | B10: Price paid | C10: Credit granted | D10: Bonus % | E10: Provider COGS (full use) | F10: Stripe fee | G10: Gross profit | H10: Net margin %
A11: Starter | B11: 10 | C11: 10 | D11: =C11/B11-1 -> 0 | E11: =C11/Assumptions!$B$5 -> 7.6923077 | F11: =B11*Assumptions!$B$6+Assumptions!$B$7 -> 0.59 | G11: =B11-E11-F11 -> 1.7176923 | H11: =G11/B11 -> 0.17176923
A12: Growth | B12: 50 | C12: 52.5 | D12: =C12/B12-1 -> 0.05 | E12: =C12/Assumptions!$B$5 -> 40.384615 | F12: =B12*Assumptions!$B$6+Assumptions!$B$7 -> 1.75 | G12: =B12-E12-F12 -> 7.8653846 | H12: =G12/B12 -> 0.15730769
A13: Professional | B13: 200 | C13: 216 | D13: =C13/B13-1 -> 0.08 | E13: =C13/Assumptions!$B$5 -> 166.15385 | F13: =B13*Assumptions!$B$6+Assumptions!$B$7 -> 6.1 | G13: =B13-E13-F13 -> 27.746154 | H13: =G13/B13 -> 0.13873077
A14: Enterprise | B14: 1000 | C14: 1120 | D14: =C14/B14-1 -> 0.12 | E14: =C14/Assumptions!$B$5 -> 861.53846 | F14: =B14*Assumptions!$B$6+Assumptions!$B$7 -> 29.3 | G14: =B14-E14-F14 -> 109.16154 | H14: =G14/B14 -> 0.10916154
A15: Note: COGS at full use = granted credit ÷ markup. Keep bonus % below the markup or a tier goes negative.

Sheet Monthly Model
A1: Monthly P&L & Break-even
A3: MONTHLY P&L (base case from Assumptions)
A4: Cash revenue | B4: =Assumptions!B17*Assumptions!B18 -> 20000
A5: Credit granted (incl. bonus) | B5: =B4*(1+Assumptions!B19) -> 21400
A6: Provider COGS (granted ÷ markup) | B6: =B5/Assumptions!B5 -> 16461.538
A7: Stripe fees | B7: =B4*Assumptions!B6+Assumptions!B17*Assumptions!B20*Assumptions!B7 -> 730
A8: Gross profit | B8: =B4-B6-B7 -> 2808.4615
A9: Gross margin % | B9: =B8/B4 -> 0.14042308
A10: Fixed monthly cost | B10: =Assumptions!B26 -> 7300
A11: Net profit / (loss) | B11: =B8-B10 -> -4491.5385 | C11: Negatives show in (parentheses)
A13: BREAK-EVEN
A14: Gross profit per user / month | B14: =B8/Assumptions!B17 -> 5.6169231
A15: Users needed to cover fixed cost | B15: =Assumptions!B26/B14 -> 1299.6439
A17: SCENARIOS
A18: Driver | B18: Conservative | C18: Base | D18: Aggressive
A19: Active paying users | B19: 150 | C19: 500 | D19: 2500
A20: Avg cash / user / month | B20: 25 | C20: 40 | D20: 60
A21: Cash revenue | B21: =B19*B20 -> 3750 | C21: =C19*C20 -> 20000 | D21: =D19*D20 -> 150000
A22: Gross profit | B22: =B21-B21*(1+Assumptions!$B$19)/Assumptions!$B$5-(B21*Assumptions!$B$6+B19*Assumptions!$B$20*Assumptions!$B$7) -> 509.71154 | C22: =C21-C21*(1+Assumptions!$B$19)/Assumptions!$B$5-(C21*Assumptions!$B$6+C19*Assumptions!$B$20*Assumptions!$B$7) -> 2808.4615 | D22: =D21-D21*(1+Assumptions!$B$19)/Assumptions!$B$5-(D21*Assumptions!$B$6+D19*Assumptions!$B$20*Assumptions!$B$7) -> 21438.462
A23: Net profit / (loss) | B23: =B22-Assumptions!$B$26 -> -6790.2885 | C23: =C22-Assumptions!$B$26 -> -4491.5385 | D23: =D22-Assumptions!$B$26 -> 14138.462
